data_retrieval_monitor/__init__.py
data_retrieval_monitor/_version.py
data_retrieval_monitor/dataset_dashboard/__init__.py
data_retrieval_monitor/dataset_dashboard/app.py
data_retrieval_monitor/dataset_dashboard/caching.py
data_retrieval_monitor/dataset_dashboard/config.py
data_retrieval_monitor/dataset_dashboard/constants.py
data_retrieval_monitor/dataset_dashboard/dashboard.py
data_retrieval_monitor/dataset_dashboard/fastpaths.py
data_retrieval_monitor/dataset_dashboard/inject.py
data_retrieval_monitor/dataset_dashboard/library.py
data_retrieval_monitor/dataset_dashboard/utils.py
data_retrieval_monitor/dataset_dashboard/components/__init__.py
data_retrieval_monitor/dataset_dashboard/components/banner.py
data_retrieval_monitor/dataset_dashboard/components/compute.py
data_retrieval_monitor/dataset_dashboard/components/controls_kpi.py
data_retrieval_monitor/dataset_dashboard/components/html.py
data_retrieval_monitor/dataset_dashboard/components/pie_chart.py
data_retrieval_monitor/dataset_dashboard/components/table.py
data_retrieval_monitor/dataset_dashboard/services/__init__.py
data_retrieval_monitor/dataset_dashboard/services/injector.py
data_retrieval_monitor/dataset_dashboard/services/logs.py
data_retrieval_monitor/dataset_dashboard/services/store.py
data_retrieval_monitor/kdb/asof_join_debug_compass.py
data_retrieval_monitor/kdb/build_taq_splayed_stoxx.py
data_retrieval_monitor/kdb/build_taq_splayed_stoxx_v2.py
data_retrieval_monitor/kdb/check_version.py
data_retrieval_monitor/kdb/duckdb.py
data_retrieval_monitor/kdb/trade_quote_classify_sliced.py
data_retrieval_monitor/kdb/trade_quote_classify_sliced_v10.py
data_retrieval_monitor/kdb/trade_quote_classify_sliced_v11.py
data_retrieval_monitor/kdb/trade_quote_classify_sliced_v12.py
data_retrieval_monitor/kdb/trade_quote_classify_sliced_v2.py
data_retrieval_monitor/kdb/trade_quote_classify_sliced_v3.py
data_retrieval_monitor/kdb/trade_quote_classify_sliced_v4.py
data_retrieval_monitor-0.8.87.dist-info/licenses/LICENSE
data_retrieval_monitor-0.8.87.dist-info/METADATA
data_retrieval_monitor-0.8.87.dist-info/WHEEL
data_retrieval_monitor-0.8.87.dist-info/top_level.txt
data_retrieval_monitor-0.8.87.dist-info/RECORD
