Metadata-Version: 2.4
Name: data-retrieval-monitor
Version: 0.8.87
Summary: Plotly Dash board to monitor data retrieval, validation, delays and failures.
Author: Donggeun Kim
License: MIT
Requires-Python: >=3.9
License-File: LICENSE
Requires-Dist: dash>=2.17.1
Requires-Dist: dash-bootstrap-components>=1.6.0
Requires-Dist: pandas>=2.2.2
Requires-Dist: python-dateutil>=2.9.0.post0
Requires-Dist: pytz>=2024.1
Requires-Dist: requests>=2.31.0
Provides-Extra: speed
Requires-Dist: polars>=1.6.0; extra == "speed"
Requires-Dist: orjson>=3.10.0; extra == "speed"
Requires-Dist: flask-compress>=1.15; extra == "speed"
Dynamic: license-file
